model_predictions/README.md
model_predictions/__init__.py
model_predictions/app.py
model_predictions/app2.py
model_predictions/constants.py
model_predictions/init_script.sh
model_predictions/requirements.txt
model_predictions/utils.py
batch_prediction-1.0.45.dist-info/METADATA
batch_prediction-1.0.45.dist-info/WHEEL
batch_prediction-1.0.45.dist-info/top_level.txt
batch_prediction-1.0.45.dist-info/RECORD
