Metadata-Version: 2.1
Name: batch-prediction
Version: 1.0.45
Summary: Batch prediction recipe
Home-page: UNKNOWN
Author: Amit Boke
License: UNKNOWN
Platform: UNKNOWN
Classifier: Programming Language :: Python :: 3.8
Requires-Python: >=3.8,<3.10
Requires-Dist: refractio[snowflake]
